{"openapi":"3.0.1","info":{"title":"Todo API","description":"A simple REST API for managing todo items","contact":{"name":"Todo API Team","url":"https://github.com/example/todo-api","email":"contact@todoapi.com"},"license":{"name":"MIT License","url":"https://opensource.org/licenses/MIT"},"version":"1.0.0"},"servers":[{"url":"http://localhost:8080","description":"Generated server url"}],"tags":[{"name":"Category Management","description":"Operations for managing categories"},{"name":"Todo Management","description":"Operations for managing todo items"}],"paths":{"/api/v1/todos/{id}":{"get":{"tags":["Todo Management"],"summary":"Get todo by ID","description":"Retrieve a specific todo item by its ID","operationId":"findById","parameters":[{"name":"id","in":"path","description":"ID of the todo to retrieve","required":true,"schema":{"type":"integer","format":"int64"}}],"responses":{"200":{"description":"Todo found","content":{"application/json":{"schema":{"$ref":"#/components/schemas/Todo"},"examples":{"Single Todo":{"description":"Single Todo","value":{"id":1,"title":"Complete project","description":"Finish the todo application","completed":false,"important":true,"category":"Work","dueDate":"2024-12-31","createdAt":"2024-01-15T10:30:00","updatedAt":"2024-01-15T10:30:00"}}}}}},"404":{"description":"Todo not found","content":{"application/json":{"schema":{"$ref":"#/components/schemas/ErrorResponse"},"examples":{"Not Found Error":{"description":"Not Found Error","value":{"status":404,"message":"Resource not found","details":"Todo not found with id: 999","timestamp":"2024-01-15T10:30:00","path":"/api/v1/todos/999"}}}}}}}},"put":{"tags":["Todo Management"],"summary":"Update todo","description":"Update an existing todo item (full replacement)","operationId":"update","parameters":[{"name":"id","in":"path","description":"ID of the todo to update","required":true,"schema":{"type":"integer","format":"int64"}}],"requestBody":{"content":{"application/json":{"schema":{"$ref":"#/components/schemas/Todo"}}},"required":true},"responses":{"404":{"description":"Todo not found","content":{"application/json":{"schema":{"$ref":"#/components/schemas/ErrorResponse"}}}},"400":{"description":"Invalid input data","content":{"application/json":{"schema":{"$ref":"#/components/schemas/ErrorResponse"}}}},"200":{"description":"Todo updated successfully","content":{"application/json":{"schema":{"$ref":"#/components/schemas/Todo"}}}}}},"delete":{"tags":["Todo Management"],"summary":"Delete todo","description":"Delete a todo item","operationId":"delete","parameters":[{"name":"id","in":"path","description":"ID of the todo to delete","required":true,"schema":{"type":"integer","format":"int64"}}],"responses":{"200":{"description":"Todo deleted successfully","content":{"application/json":{"schema":{"$ref":"#/components/schemas/DeleteResponse"},"examples":{"Delete Confirmation":{"description":"Delete Confirmation","value":{"message":"Todo successfully deleted","deletedId":1}}}}}},"404":{"description":"Todo not found","content":{"application/json":{"schema":{"$ref":"#/components/schemas/ErrorResponse"}}}}}},"patch":{"tags":["Todo Management"],"summary":"Partial update todo","description":"Update specific fields of a todo item (only provided fields will be updated)","operationId":"patchTodo","parameters":[{"name":"id","in":"path","description":"ID of the todo to update","required":true,"schema":{"type":"integer","format":"int64"}}],"requestBody":{"content":{"application/json":{"schema":{"$ref":"#/components/schemas/TodoUpdateRequest"}}},"required":true},"responses":{"200":{"description":"Todo updated successfully","content":{"application/json":{"schema":{"$ref":"#/components/schemas/Todo"},"examples":{"Patched Todo":{"description":"Patched Todo","value":{"id":1,"title":"Complete project","description":"Finish the todo application","completed":true,"important":true,"category":"Work","dueDate":"2024-12-31","createdAt":"2024-01-15T10:30:00","updatedAt":"2024-01-15T11:00:00"}}}}}},"404":{"description":"Todo not found","content":{"application/json":{"schema":{"$ref":"#/components/schemas/ErrorResponse"}}}},"400":{"description":"Invalid input data","content":{"application/json":{"schema":{"$ref":"#/components/schemas/ErrorResponse"}}}}}}},"/api/v1/todos":{"get":{"tags":["Todo Management"],"summary":"Get all todos","description":"Retrieve all todo items with optional filtering and search","operationId":"list","parameters":[{"name":"completed","in":"query","description":"Filter by completion status","required":false,"schema":{"type":"boolean"}},{"name":"category","in":"query","description":"Filter by category name","required":false,"schema":{"type":"string"}},{"name":"important","in":"query","description":"Filter by important status","required":false,"schema":{"type":"boolean"}},{"name":"dueDate","in":"query","description":"Filter by due date (YYYY-MM-DD)","required":false,"schema":{"type":"string","format":"date"}},{"name":"q","in":"query","description":"Search term to find in title or description","required":false,"schema":{"type":"string"}}],"responses":{"200":{"description":"Successfully retrieved todos","content":{"application/json":{"schema":{"$ref":"#/components/schemas/Todo"},"examples":{"Todo List":{"description":"Todo List","value":[{"id":1,"title":"Complete project","description":"Finish the todo application","completed":false,"important":true,"category":"Work","dueDate":"2024-12-31","createdAt":"2024-01-15T10:30:00","updatedAt":"2024-01-15T10:30:00"}]}}}}}}},"post":{"tags":["Todo Management"],"summary":"Create new todo","description":"Create a new todo item","operationId":"create","requestBody":{"content":{"application/json":{"schema":{"$ref":"#/components/schemas/Todo"}}},"required":true},"responses":{"400":{"description":"Invalid input data","content":{"application/json":{"schema":{"$ref":"#/components/schemas/ErrorResponse"},"examples":{"Validation Error":{"description":"Validation Error","value":{"status":400,"message":"Validation failed","details":"Title is required","timestamp":"2024-01-15T10:30:00","path":"/api/v1/todos"}}}}}},"201":{"description":"Todo created successfully","content":{"application/json":{"schema":{"$ref":"#/components/schemas/Todo"},"examples":{"Created Todo":{"description":"Created Todo","value":{"id":1,"title":"New Task","description":"Task description","completed":false,"important":false,"category":"Personal","dueDate":null,"createdAt":"2024-01-15T10:30:00","updatedAt":"2024-01-15T10:30:00"}}}}}}}}},"/api/v1/categories":{"get":{"tags":["Category Management"],"summary":"Get all categories","description":"Retrieve all categories","operationId":"getAllCategories","responses":{"200":{"description":"Successfully retrieved categories","content":{"application/json":{"schema":{"$ref":"#/components/schemas/Category"},"examples":{"Category List":{"description":"Category List","value":[{"id":1,"name":"Work","description":"Work-related tasks","createdAt":"2024-01-15T10:30:00"},{"id":2,"name":"Personal","description":"Personal tasks","createdAt":"2024-01-15T10:35:00"}]}}}}}}},"post":{"tags":["Category Management"],"summary":"Create new category","description":"Create a new category","operationId":"createCategory","requestBody":{"content":{"application/json":{"schema":{"$ref":"#/components/schemas/Category"}}},"required":true},"responses":{"201":{"description":"Category created successfully","content":{"application/json":{"schema":{"$ref":"#/components/schemas/Category"}}}},"409":{"description":"Category with this name already exists","content":{"application/json":{"schema":{"$ref":"#/components/schemas/ErrorResponse"}}}},"400":{"description":"Invalid input data","content":{"application/json":{"schema":{"$ref":"#/components/schemas/ErrorResponse"}}}}}}},"/api/v1/todos/today":{"get":{"tags":["Todo Management"],"summary":"Get today's todos","description":"Retrieve todos due today","operationId":"getTodaysTodos","parameters":[{"name":"completed","in":"query","description":"Filter by completion status","required":false,"schema":{"type":"boolean"}}],"responses":{"200":{"description":"Today's todos retrieved","content":{"application/json":{"schema":{"$ref":"#/components/schemas/Todo"},"examples":{"Today's Todos":{"description":"Today's Todos","value":[{"id":1,"title":"Daily standup","description":"Team meeting","completed":false,"important":true,"category":"Work","dueDate":"2024-01-15","createdAt":"2024-01-15T08:00:00","updatedAt":"2024-01-15T08:00:00"}]}}}}}}}}},"components":{"schemas":{"Todo":{"required":["title"],"type":"object","properties":{"id":{"type":"integer","description":"Unique identifier of the todo","format":"int64","readOnly":true,"example":1},"title":{"maxLength":100,"minLength":0,"type":"string","description":"Title of the todo","example":"Buy groceries"},"description":{"maxLength":500,"minLength":0,"type":"string","description":"Description of the todo","example":"Buy milk, bread, and eggs"},"completed":{"type":"boolean","description":"Completion status of the todo","example":false},"createdAt":{"type":"string","description":"Creation timestamp","format":"date-time","readOnly":true},"updatedAt":{"type":"string","description":"Last update timestamp","format":"date-time","readOnly":true},"category":{"maxLength":50,"minLength":0,"type":"string","description":"Category of the todo","example":"Personal"},"important":{"type":"boolean","description":"Important status of the todo","example":false},"dueDate":{"type":"string","description":"Due date of the todo (YYYY-MM-DD format)","format":"date","example":"2024-01-15"}},"description":"Todo item","example":{"id":1,"title":"Complete project","description":"Finish the todo application","completed":false,"important":true,"category":"Work","dueDate":"2024-12-31","createdAt":"2024-01-15T10:30:00","updatedAt":"2024-01-15T10:30:00"}},"ErrorResponse":{"type":"object","properties":{"status":{"type":"integer","description":"HTTP status code","format":"int32","example":404},"message":{"type":"string","description":"Error message","example":"Resource not found"},"details":{"type":"string","description":"Error details","example":"Todo with id 123 not found"},"timestamp":{"type":"string","description":"Timestamp when the error occurred","format":"date-time"},"path":{"type":"string","description":"Request path","example":"/api/v1/todos/123"}},"description":"Error response structure"},"Category":{"required":["name"],"type":"object","properties":{"id":{"type":"integer","description":"Unique identifier of the category","format":"int64","example":1},"name":{"maxLength":50,"minLength":0,"type":"string","description":"Name of the category","example":"Personal"},"description":{"maxLength":200,"minLength":0,"type":"string","description":"Description of the category","example":"Personal tasks and activities"},"createdAt":{"type":"string","description":"Creation timestamp","format":"date-time"}},"description":"Category for organizing todos"},"TodoUpdateRequest":{"type":"object","properties":{"title":{"maxLength":100,"minLength":0,"type":"string","description":"Updated title of the todo","example":"Updated task title"},"description":{"maxLength":500,"minLength":0,"type":"string","description":"Updated description of the todo","example":"Updated detailed description"},"completed":{"type":"boolean","description":"Updated completion status","example":true},"important":{"type":"boolean","description":"Updated important status","example":false},"category":{"maxLength":50,"minLength":0,"type":"string","description":"Updated category","example":"Work"},"dueDate":{"type":"string","description":"Updated due date (YYYY-MM-DD format)","format":"date","example":"2024-01-15"}},"description":"Fields to update (only non-null fields will be updated)","example":{"completed":true,"important":false,"title":"Updated task"}},"DeleteResponse":{"type":"object","properties":{"message":{"type":"string","description":"Confirmation message","example":"Todo successfully deleted"},"deletedId":{"type":"integer","description":"ID of the deleted resource","format":"int64","example":1}},"description":"Response for successful delete operation","example":{"message":"Todo successfully deleted","deletedId":1}}}}}